exceltypes/__init__.py
exceltypes/gen_py/_00020813_0000_0000_C000_000000000046x0x1x9.py
exceltypes/gen_py/_2DF8D04C_5BFA_101B_BDE5_00AA0044DE52x0x2x8.py
exceltypes/gen_py/__init__.py
exceltypes-0.0.2.dist-info/LICENSE.md
exceltypes-0.0.2.dist-info/METADATA
exceltypes-0.0.2.dist-info/WHEEL
exceltypes-0.0.2.dist-info/top_level.txt
exceltypes-0.0.2.dist-info/RECORD
