Metadata-Version: 2.1
Name: exceltypes
Version: 0.0.2
Summary: Type annotations for Excel types using win32com / pywin32
Home-page: UNKNOWN
License: UNKNOWN
Project-URL: Source, https://github.com/pyxll/exceltypes
Project-URL: Tracker, https://github.com/pyxll/exceltypes/issues
Platform: UNKNOWN
Classifier: Programming Language :: Python :: 3
Classifier: License :: OSI Approved :: MIT License
Classifier: Operating System :: Microsoft :: Windows
Requires-Python: >=3.8.0
Requires-Dist: pywin32
